{
    "name": "Vampire's Fragrance",
    "cost": "0",
    "costType": "ep",
    "requiredLevel": "0",
    "learningCost": "0",
    "skillType": "statusEffect",
    "statType": "Allure",
    "statusEffectScaling": "0",
    "requiredStat": "0",
    "skillTags": ["Seduction", "Magic"],
    "fetishTags": [""],
    "startsStance": [""],
    "requiresStance": "Any",
    "unusableIfStance": ["Any"],
    "requiresTargetStance": [ "Any"],
    "unusableIfTarget": [""],
    "removesStance": ["None"],
    "requiresStatusEffect": "None",
    "requiresStatusPotency": "0",
    "unusableIfStatusEffect": [ "None"],
    "requiresStatusEffectSelf": "None",
    "requiresStatusPotencySelf": "0",
    "unusableIfStatusEffectSelf": [ "None"],
    "requiresPerk": [ ],
    "requiresOnePerk": [ ],
    "unusableIfPerk": [ ],
    "requiresPerkSelf": [ ],
    "requiresOnePerkSelf": [ ],
    "unusableIfPerkSelf": [ ],
    "power": "0",
    "minRange": "100",
    "maxRange": "100",
    "recoil": "0",
    "critChance": "0",
    "critDamage": "0",
    "targetType": "single",
    "accuracy": "0",
    "initiative": "0",
    "statusEffect": "Aphrodisiac",
    "statusChance": "999",
    "statusDuration": "8",
    "statusPotency": "8",
    "statusResistedBy": "Willpower",
    "statusText": "aphrodisiac",
    "descrip": "Loretta's general aphrodisiac applier skill.",
    "outcome": "",
    "miss": "",
    "statusOutcome": "",
    "statusMiss": "",
    "restraintStruggle": [""],
    "restraintStruggleCharmed": [""],
    "restraintEscaped": [""],
    "restraintEscapedFail": [""]
}
